.gitignore
.gitreview
setup.py
nosclient/__init__.py
nosclient/call_nos_driver.py
nosclient/nos.py
nosclient/nt_version.py
nosclient/operate_chunk_image.py
nosclient/operate_private_key.py
nosclient/tests/__init__.py
nosclient/tests/fake_context.py
nosclient/tests/test_nos.py
nosclient/tests/test_operate_chunk_image.py
nosclient/tests/test_operate_private_key.py
python_nosclient.egg-info/PKG-INFO
python_nosclient.egg-info/SOURCES.txt
python_nosclient.egg-info/dependency_links.txt
python_nosclient.egg-info/top_level.txt