Metadata-Version: 1.1
Name: python-nosclient
Version: 1.1
Summary: Python client for Netease-NOS
Home-page: UNKNOWN
Author: hzyangtk
Author-email: hzyangtk@corp.netease.com
License: UNKNOWN
Platform: UNKNOWN
Classifier: License :: OSI Approved :: Apache Software License
Classifier: Operating System :: POSIX :: Linux
Classifier: Programming Language :: Python :: 2.6
Classifier: Environment :: No Input/Output (Daemon)
